kleptes/__init__.py
kleptes/_version.py
kleptes/eurostat.py
kleptes/goodies.py
kleptes/oecd.py
kleptes/utils.py
kleptes/wb.py
kleptes/who.py
kleptes/yf.py
kleptes-0.5.dist-info/DESCRIPTION.rst
kleptes-0.5.dist-info/METADATA
kleptes-0.5.dist-info/RECORD
kleptes-0.5.dist-info/WHEEL
kleptes-0.5.dist-info/metadata.json
kleptes-0.5.dist-info/top_level.txt
