Metadata-Version: 2.0
Name: kleptes
Version: 0.5
Summary: Goodies to mine world data
Home-page: UNKNOWN
Author: myyc
Author-email: UNKNOWN
License: BSD
Keywords: data mining python pandas who oecd
Platform: UNKNOWN
Classifier: Development Status :: 2 - Pre-Alpha
Classifier: Topic :: Utilities
Classifier: License :: OSI Approved :: BSD License
Requires-Dist: bs4
Requires-Dist: mnemon
Requires-Dist: pandas
Requires-Dist: pendulum
Requires-Dist: requests
